{
  "comforts:sleeping_bag_light_blue": {
    "criteria": {
      "has_the_recipe": "2024-10-25 22:07:01 -0300"
    },
    "done": true
  },
  "enigmaticlegacy:book/misc/cosmic_cake": {
    "criteria": {
      "has_the_recipe": "2024-10-25 22:07:01 -0300"
    },
    "done": true
  },
  "enigmaticlegacy:book/accessories/enigmatic_elytra": {
    "criteria": {
      "has_the_recipe": "2024-10-25 22:07:01 -0300"
    },
    "done": true
  },
  "enigmaticlegacy:book/misc/mega_sponge": {
    "criteria": {
      "has_the_recipe": "2024-10-25 22:07:01 -0300"
    },
    "done": true
  },
  "enigmaticlegacy:book/misc/hunter_guidebook": {
    "criteria": {
      "has_the_recipe": "2024-10-25 22:07:01 -0300"
    },
    "done": true
  },
  "comforts:hammock_purple": {
    "criteria": {
      "has_the_recipe": "2024-10-25 22:07:01 -0300"
    },
    "done": true
  },
  "comforts:sleeping_bag_pink": {
    "criteria": {
      "has_the_recipe": "2024-10-25 22:07:01 -0300"
    },
    "done": true
  },
  "comforts:hammock_magenta": {
    "criteria": {
      "has_the_recipe": "2024-10-25 22:07:01 -0300"
    },
    "done": true
  },
  "enigmaticlegacy:book/accessories/escape_scroll": {
    "criteria": {
      "has_the_recipe": "2024-10-25 22:07:01 -0300"
    },
    "done": true
  },
  "enigmaticlegacy:book/accessories/iron_ring": {
    "criteria": {
      "has_the_recipe": "2024-10-25 22:07:01 -0300"
    },
    "done": true
  },
  "enigmaticlegacy:book/materials/cosmic_heart": {
    "criteria": {
      "has_the_recipe": "2024-10-25 22:07:01 -0300"
    },
    "done": true
  },
  "comforts:hammock_red": {
    "criteria": {
      "has_the_recipe": "2024-10-25 22:07:01 -0300"
    },
    "done": true
  },
  "enigmaticlegacy:book/misc/enchantment_transposer": {
    "criteria": {
      "has_the_recipe": "2024-10-25 22:07:01 -0300"
    },
    "done": true
  },
  "comforts:sleeping_bag_white": {
    "criteria": {
      "has_the_recipe": "2024-10-25 22:07:01 -0300"
    },
    "done": true
  },
  "comforts:sleeping_bag_gray": {
    "criteria": {
      "has_the_recipe": "2024-10-25 22:07:01 -0300"
    },
    "done": true
  },
  "enigmaticlegacy:book/tools/ender_slayer": {
    "criteria": {
      "has_the_recipe": "2024-10-25 22:07:01 -0300"
    },
    "done": true
  },
  "comforts:rope_and_nail": {
    "criteria": {
      "has_the_recipe": "2024-10-25 22:07:01 -0300"
    },
    "done": true
  },
  "enigmaticlegacy:book/accessories/ender_ring": {
    "criteria": {
      "has_the_recipe": "2024-10-25 22:07:01 -0300"
    },
    "done": true
  },
  "enigmaticlegacy:book/misc/infinimeal": {
    "criteria": {
      "has_the_recipe": "2024-10-25 22:07:01 -0300"
    },
    "done": true
  },
  "comforts:sleeping_bag_cyan": {
    "criteria": {
      "has_the_recipe": "2024-10-25 22:07:01 -0300"
    },
    "done": true
  },
  "enigmaticlegacy:book/misc/animal_guidebook": {
    "criteria": {
      "has_the_recipe": "2024-10-25 22:07:01 -0300"
    },
    "done": true
  },
  "enigmaticlegacy:book/misc/extradimensional_eye": {
    "criteria": {
      "has_the_recipe": "2024-10-25 22:07:01 -0300"
    },
    "done": true
  },
  "enigmaticlegacy:book/accessories/heaven_scroll": {
    "criteria": {
      "has_the_recipe": "2024-10-25 22:07:01 -0300"
    },
    "done": true
  },
  "enigmaticlegacy:book/misc/end_anchor": {
    "criteria": {
      "has_the_recipe": "2024-10-25 22:07:01 -0300"
    },
    "done": true
  },
  "comforts:sleeping_bag_light_gray": {
    "criteria": {
      "has_the_recipe": "2024-10-25 22:07:01 -0300"
    },
    "done": true
  },
  "comforts:hammock_black": {
    "criteria": {
      "has_the_recipe": "2024-10-25 22:07:01 -0300"
    },
    "done": true
  },
  "enigmaticlegacy:book/misc/astral_potato": {
    "criteria": {
      "has_the_recipe": "2024-10-25 22:07:01 -0300"
    },
    "done": true
  },
  "enigmaticlegacy:book/accessories/magnet_ring": {
    "criteria": {
      "has_the_recipe": "2024-10-25 22:07:01 -0300"
    },
    "done": true
  },
  "enigmaticlegacy:book/misc/soul_compass": {
    "criteria": {
      "has_the_recipe": "2024-10-25 22:07:01 -0300"
    },
    "done": true
  },
  "enigmaticlegacy:book/misc/lore_inscriber": {
    "criteria": {
      "has_the_recipe": "2024-10-25 22:07:01 -0300"
    },
    "done": true
  },
  "comforts:hammock_gray": {
    "criteria": {
      "has_the_recipe": "2024-10-25 22:07:01 -0300"
    },
    "done": true
  },
  "comforts:hammock_cyan": {
    "criteria": {
      "has_the_recipe": "2024-10-25 22:07:01 -0300"
    },
    "done": true
  },
  "comforts:sleeping_bag_purple": {
    "criteria": {
      "has_the_recipe": "2024-10-25 22:07:01 -0300"
    },
    "done": true
  },
  "comforts:sleeping_bag_green": {
    "criteria": {
      "has_the_recipe": "2024-10-25 22:07:01 -0300"
    },
    "done": true
  },
  "comforts:hammock_light_blue": {
    "criteria": {
      "has_the_recipe": "2024-10-25 22:07:01 -0300"
    },
    "done": true
  },
  "enigmaticlegacy:book/accessories/xp_scroll": {
    "criteria": {
      "has_the_recipe": "2024-10-25 22:07:01 -0300"
    },
    "done": true
  },
  "enigmaticlegacy:book/decorations/lamp": {
    "criteria": {
      "has_the_recipe": "2024-10-25 22:07:01 -0300"
    },
    "done": true
  },
  "enigmaticlegacy:book/tools/infernal_shield": {
    "criteria": {
      "has_the_recipe": "2024-10-25 22:07:01 -0300"
    },
    "done": true
  },
  "comforts:sleeping_bag_magenta": {
    "criteria": {
      "has_the_recipe": "2024-10-25 22:07:01 -0300"
    },
    "done": true
  },
  "comforts:hammock_green": {
    "criteria": {
      "has_the_recipe": "2024-10-25 22:07:01 -0300"
    },
    "done": true
  },
  "enigmaticlegacy:book/tools/etherium_axe": {
    "criteria": {
      "has_the_recipe": "2024-10-25 22:07:01 -0300"
    },
    "done": true
  },
  "comforts:sleeping_bag_black": {
    "criteria": {
      "has_the_recipe": "2024-10-25 22:07:01 -0300"
    },
    "done": true
  },
  "enigmaticlegacy:book/accessories/fabulous_scroll": {
    "criteria": {
      "has_the_recipe": "2024-10-25 22:07:01 -0300"
    },
    "done": true
  },
  "enigmaticlegacy:book/misc/twisted_mirror": {
    "criteria": {
      "has_the_recipe": "2024-10-25 22:07:01 -0300"
    },
    "done": true
  },
  "enigmaticlegacy:book/misc/mending_mixture": {
    "criteria": {
      "has_the_recipe": "2024-10-25 22:07:01 -0300"
    },
    "done": true
  },
  "enigmaticlegacy:book/decorations/shroomlamp": {
    "criteria": {
      "has_the_recipe": "2024-10-25 22:07:01 -0300"
    },
    "done": true
  },
  "comforts:hammock_lime": {
    "criteria": {
      "has_the_recipe": "2024-10-25 22:07:01 -0300"
    },
    "done": true
  },
  "enigmaticlegacy:book/accessories/enchanter_pearl": {
    "criteria": {
      "has_the_recipe": "2024-10-25 22:07:01 -0300"
    },
    "done": true
  },
  "enigmaticlegacy:book/accessories/golden_ring": {
    "criteria": {
      "has_the_recipe": "2024-10-25 22:07:01 -0300"
    },
    "done": true
  },
  "comforts:sleeping_bag_red": {
    "criteria": {
      "has_the_recipe": "2024-10-25 22:07:01 -0300"
    },
    "done": true
  },
  "comforts:sleeping_bag_orange": {
    "criteria": {
      "has_the_recipe": "2024-10-25 22:07:01 -0300"
    },
    "done": true
  },
  "enigmaticlegacy:book/tools/etherium_sword": {
    "criteria": {
      "has_the_recipe": "2024-10-25 22:07:01 -0300"
    },
    "done": true
  },
  "enigmaticlegacy:book/armor/etherium_armor": {
    "criteria": {
      "has_the_recipe2": "2024-10-25 22:07:01 -0300"
    },
    "done": true
  },
  "enigmaticlegacy:book/tools/forbidden_axe": {
    "criteria": {
      "has_the_recipe": "2024-10-25 22:07:01 -0300"
    },
    "done": true
  },
  "comforts:hammock_blue": {
    "criteria": {
      "has_the_recipe": "2024-10-25 22:07:01 -0300"
    },
    "done": true
  },
  "comforts:hammock_white": {
    "criteria": {
      "has_the_recipe": "2024-10-25 22:07:01 -0300"
    },
    "done": true
  },
  "enigmaticlegacy:book/tools/the_twist": {
    "criteria": {
      "has_the_recipe": "2024-10-25 22:07:01 -0300"
    },
    "done": true
  },
  "enigmaticlegacy:book/tools/etherium_scythe": {
    "criteria": {
      "has_the_recipe": "2024-10-25 22:07:01 -0300"
    },
    "done": true
  },
  "comforts:hammock_light_gray": {
    "criteria": {
      "has_the_recipe": "2024-10-25 22:07:01 -0300"
    },
    "done": true
  },
  "enigmaticlegacy:book/accessories/mining_charm": {
    "criteria": {
      "has_the_recipe": "2024-10-25 22:07:01 -0300"
    },
    "done": true
  },
  "comforts:sleeping_bag_brown": {
    "criteria": {
      "has_the_recipe": "2024-10-25 22:07:01 -0300"
    },
    "done": true
  },
  "enigmaticlegacy:book/decorations/redstone_lantern": {
    "criteria": {
      "has_the_recipe": "2024-10-25 22:07:01 -0300"
    },
    "done": true
  },
  "comforts:hammock_pink": {
    "criteria": {
      "has_the_recipe": "2024-10-25 22:07:01 -0300"
    },
    "done": true
  },
  "comforts:hammock_brown": {
    "criteria": {
      "has_the_recipe": "2024-10-25 22:07:01 -0300"
    },
    "done": true
  },
  "enigmaticlegacy:book/tools/the_infinitum": {
    "criteria": {
      "has_the_recipe": "2024-10-25 22:07:01 -0300"
    },
    "done": true
  },
  "comforts:sleeping_bag_lime": {
    "criteria": {
      "has_the_recipe": "2024-10-25 22:07:01 -0300"
    },
    "done": true
  },
  "enigmaticlegacy:book/tools/eldritch_pan": {
    "criteria": {
      "has_the_recipe": "2024-10-25 22:07:01 -0300"
    },
    "done": true
  },
  "enigmaticlegacy:book/accessories/super_magnet_ring": {
    "criteria": {
      "has_the_recipe": "2024-10-25 22:07:01 -0300"
    },
    "done": true
  },
  "comforts:hammock_yellow": {
    "criteria": {
      "has_the_recipe": "2024-10-25 22:07:01 -0300"
    },
    "done": true
  },
  "enigmaticlegacy:book/accessories/arcane_scrolls": {
    "criteria": {
      "has_the_recipe": "2024-10-25 22:07:01 -0300"
    },
    "done": true
  },
  "enigmaticlegacy:book/accessories/avarice_scroll": {
    "criteria": {
      "has_the_recipe": "2024-10-25 22:07:01 -0300"
    },
    "done": true
  },
  "enigmaticlegacy:book/tools/etherium_shovel": {
    "criteria": {
      "has_the_recipe": "2024-10-25 22:07:01 -0300"
    },
    "done": true
  },
  "comforts:sleeping_bag_blue": {
    "criteria": {
      "has_the_recipe": "2024-10-25 22:07:01 -0300"
    },
    "done": true
  },
  "progressivebosses:recipes/misc/corrupted_soul_sand": {
    "criteria": {
      "has_the_recipe_3": "2024-10-25 22:07:01 -0300"
    },
    "done": true
  },
  "enigmaticlegacy:book/tools/etherium_pickaxe": {
    "criteria": {
      "has_the_recipe": "2024-10-25 22:07:01 -0300"
    },
    "done": true
  },
  "enigmaticlegacy:book/accessories/monster_charm": {
    "criteria": {
      "has_the_recipe": "2024-10-25 22:07:01 -0300"
    },
    "done": true
  },
  "enigmaticlegacy:book/accessories/desolation_ring": {
    "criteria": {
      "has_the_recipe": "2024-10-25 22:07:01 -0300"
    },
    "done": true
  },
  "comforts:sleeping_bag_yellow": {
    "criteria": {
      "has_the_recipe": "2024-10-25 22:07:01 -0300"
    },
    "done": true
  },
  "mythicmounts:summoning_staff": {
    "criteria": {
      "has_the_recipe": "2024-10-25 22:07:01 -0300"
    },
    "done": true
  },
  "enigmaticlegacy:book/accessories/berserk_charm": {
    "criteria": {
      "has_the_recipe": "2024-10-25 22:07:01 -0300"
    },
    "done": true
  },
  "enigmaticlegacy:book/materials/twisted_heart": {
    "criteria": {
      "has_the_recipe": "2024-10-25 22:07:01 -0300"
    },
    "done": true
  },
  "enigmaticlegacy:book/accessories/insignia": {
    "criteria": {
      "has_the_recipe": "2024-10-25 22:07:01 -0300"
    },
    "done": true
  },
  "enigmaticlegacy:book/materials/ender_rod": {
    "criteria": {
      "has_the_recipe": "2024-10-25 22:07:01 -0300"
    },
    "done": true
  },
  "enigmaticlegacy:book/accessories/cursed_scroll": {
    "criteria": {
      "has_the_recipe": "2024-10-25 22:07:01 -0300"
    },
    "done": true
  },
  "enigmaticlegacy:book/misc/curse_transposer": {
    "criteria": {
      "has_the_recipe": "2024-10-25 22:07:01 -0300"
    },
    "done": true
  },
  "enigmaticlegacy:book/tools/astral_breaker": {
    "criteria": {
      "has_the_recipe": "2024-10-25 22:07:01 -0300"
    },
    "done": true
  },
  "comforts:hammock_orange": {
    "criteria": {
      "has_the_recipe": "2024-10-25 22:07:01 -0300"
    },
    "done": true
  },
  "enigmaticlegacy:book/misc/cursed_stone": {
    "criteria": {
      "has_the_recipe": "2024-10-25 22:07:01 -0300"
    },
    "done": true
  },
  "iceandfire:iceandfire/root": {
    "criteria": {
      "tick": "2024-10-25 22:07:02 -0300"
    },
    "done": true
  },
  "rpg_series:root": {
    "criteria": {
      "always": "2024-10-25 22:07:02 -0300"
    },
    "done": true
  },
  "takesapillage:root": {
    "criteria": {
      "always": "2024-10-25 22:07:02 -0300"
    },
    "done": true
  },
  "morevillagers:root": {
    "criteria": {
      "always": "2024-10-25 22:07:02 -0300"
    },
    "done": true
  },
  "battletowers:root": {
    "criteria": {
      "Tick": "2024-10-25 22:07:02 -0300"
    },
    "done": true
  },
  "mobs_of_mythology:mobs_of_mythology": {
    "criteria": {
      "tick": "2024-10-25 22:07:02 -0300"
    },
    "done": true
  },
  "biomeswevegone:biomeswevegone/root": {
    "criteria": {
      "tick": "2024-10-25 22:07:02 -0300"
    },
    "done": true
  },
  "dungeons_arise:wda_root": {
    "criteria": {
      "WDA": "2024-10-25 22:07:02 -0300"
    },
    "done": true
  },
  "legendary_monsters:end_root": {
    "criteria": {
      "custom_test_name": "2024-10-25 22:07:02 -0300"
    },
    "done": true
  },
  "repurposed_structures:root": {
    "criteria": {
      "always": "2024-10-25 22:07:02 -0300"
    },
    "done": true
  },
  "miningmaster:miningmaster/root": {
    "criteria": {
      "tick": "2024-10-25 22:07:02 -0300"
    },
    "done": true
  },
  "mowziesmobs:root": {
    "criteria": {
      "custom_test_name": "2024-10-25 22:07:02 -0300"
    },
    "done": true
  },
  "betterdungeons:root": {
    "criteria": {
      "always": "2024-10-25 22:07:02 -0300"
    },
    "done": true
  },
  "lootr:root": {
    "criteria": {
      "always_true": "2024-10-25 22:07:02 -0300"
    },
    "done": true
  },
  "legendary_monsters:legendary_monsters_root": {
    "criteria": {
      "custom_test_name": "2024-10-25 22:07:02 -0300"
    },
    "done": true
  },
  "born_in_chaos_v1:bornin_chaos": {
    "criteria": {
      "bornin_chaos_0": "2024-10-25 22:07:02 -0300"
    },
    "done": true
  },
  "legendary_monsters:nether_root": {
    "criteria": {
      "custom_test_name": "2024-10-25 22:07:02 -0300"
    },
    "done": true
  },
  "cataclysm:root": {
    "criteria": {
      "custom_test_name": "2024-10-25 22:07:02 -0300"
    },
    "done": true
  },
  "minecraft:adventure/adventuring_time": {
    "criteria": {
      "minecraft:snowy_slopes": "2024-10-26 10:36:16 -0300",
      "minecraft:old_growth_pine_taiga": "2024-10-26 00:47:11 -0300",
      "minecraft:taiga": "2024-10-26 10:19:38 -0300",
      "minecraft:deep_ocean": "2024-10-25 22:09:51 -0300",
      "minecraft:sunflower_plains": "2024-10-25 22:07:11 -0300",
      "minecraft:beach": "2024-10-25 22:08:55 -0300",
      "minecraft:stony_peaks": "2024-10-27 16:29:00 -0300",
      "minecraft:river": "2024-10-26 17:14:16 -0300",
      "minecraft:stony_shore": "2024-10-25 22:20:51 -0300",
      "minecraft:cold_ocean": "2024-10-26 23:48:02 -0300",
      "minecraft:forest": "2024-10-26 00:24:44 -0300",
      "minecraft:deep_cold_ocean": "2024-10-26 23:48:28 -0300",
      "minecraft:ocean": "2024-10-25 22:09:17 -0300",
      "minecraft:frozen_peaks": "2024-10-26 15:30:25 -0300",
      "minecraft:old_growth_birch_forest": "2024-10-26 00:25:34 -0300",
      "minecraft:deep_dark": "2024-10-26 21:25:33 -0300",
      "minecraft:plains": "2024-10-26 10:25:44 -0300"
    },
    "done": false
  },
  "regions_unexplored:parent": {
    "criteria": {
      "load_in_world": "2024-10-25 22:07:11 -0300"
    },
    "done": true
  },
  "biomeswevegone:biomeswevegone/husbandry/johnny_appleseed": {
    "criteria": {
      "apple": "2024-10-25 22:08:25 -0300",
      "golden_apple": "2024-10-25 22:47:44 -0300"
    },
    "done": false
  },
  "mostructures:root": {
    "criteria": {
      "very_simple_trigger": "2024-10-25 22:08:25 -0300"
    },
    "done": true
  },
  "theabyss:unlockthebook": {
    "criteria": {
      "unlockthebook": "2024-10-25 22:08:30 -0300"
    },
    "done": true
  },
  "aquamirae:adventure/root": {
    "criteria": {
      "crafting_table": "2024-10-25 22:08:30 -0300"
    },
    "done": true
  },
  "minecraft:story/root": {
    "criteria": {
      "crafting_table": "2024-10-25 22:08:30 -0300"
    },
    "done": true
  },
  "soulsweapons:root": {
    "criteria": {
      "crafting_table": "2024-10-25 22:08:30 -0300"
    },
    "done": true
  },
  "mostructures:pirate_ship": {
    "criteria": {
      "pillager_factory": "2024-10-25 22:09:54 -0300"
    },
    "done": true
  },
  "minecraft:adventure/root": {
    "criteria": {
      "killed_by_something": "2024-10-25 22:13:22 -0300"
    },
    "done": true
  },
  "regions_unexplored:spelunker": {
    "criteria": {
      "ancient_delta": "2024-10-25 22:20:47 -0300"
    },
    "done": false
  },
  "regions_unexplored:regions_explored": {
    "criteria": {
      "shrubland": "2024-10-26 00:21:05 -0300",
      "pine_taiga": "2024-10-26 17:13:18 -0300",
      "ancient_delta": "2024-10-25 22:20:47 -0300",
      "grassy_beach": "2024-10-26 17:15:53 -0300",
      "blackwood_taiga": "2024-10-26 17:14:31 -0300",
      "ochard": "2024-10-26 00:17:39 -0300",
      "highland_fields": "2024-10-26 00:21:17 -0300",
      "sparse_redwoods": "2024-10-26 17:15:47 -0300",
      "deciduous_forest": "2024-10-27 16:29:03 -0300",
      "redwoods": "2024-10-26 17:13:54 -0300"
    },
    "done": false
  },
  "minecraft:adventure/sleep_in_bed": {
    "criteria": {
      "slept_in_bed": "2024-10-25 22:23:41 -0300"
    },
    "done": true
  },
  "minecraft:story/upgrade_tools": {
    "criteria": {
      "stone_pickaxe": "2024-10-25 22:25:47 -0300"
    },
    "done": true
  },
  "minecraft:story/smelt_iron": {
    "criteria": {
      "iron": "2024-10-25 22:27:22 -0300"
    },
    "done": true
  },
  "wrd:wesleys_roguelike_dungeons": {
    "criteria": {
      "wesleys_roguelike_dungeons": "2024-10-25 22:27:22 -0300"
    },
    "done": true
  },
  "minecraft:story/mine_stone": {
    "criteria": {
      "get_stone": "2024-10-25 22:29:18 -0300"
    },
    "done": true
  },
  "minecraft:adventure/kill_all_mobs": {
    "criteria": {
      "minecraft:pillager": "2024-10-26 15:33:46 -0300",
      "minecraft:skeleton": "2024-10-25 22:31:56 -0300",
      "minecraft:magma_cube": "2024-10-25 23:21:37 -0300",
      "minecraft:spider": "2024-10-26 15:08:12 -0300",
      "minecraft:creeper": "2024-10-26 00:29:44 -0300",
      "minecraft:witch": "2024-10-26 00:30:01 -0300",
      "minecraft:husk": "2024-10-26 00:48:03 -0300",
      "minecraft:cave_spider": "2024-10-26 17:26:55 -0300",
      "minecraft:silverfish": "2024-10-25 23:18:42 -0300",
      "minecraft:stray": "2024-10-25 22:40:15 -0300",
      "minecraft:zombie": "2024-10-25 22:29:49 -0300",
      "minecraft:zombie_villager": "2024-10-26 16:59:42 -0300"
    },
    "done": false
  },
  "minecraft:adventure/kill_a_mob": {
    "criteria": {
      "minecraft:zombie": "2024-10-25 22:29:49 -0300"
    },
    "done": true
  },
  "biomeswevegone:biomeswevegone/husbandry/root": {
    "criteria": {
      "consumed_item": "2024-10-25 22:42:35 -0300"
    },
    "done": true
  },
  "minecraft:husbandry/balanced_diet": {
    "criteria": {
      "cooked_beef": "2024-10-26 15:26:38 -0300",
      "cooked_cod": "2024-10-25 22:42:35 -0300",
      "pumpkin_pie": "2024-10-25 23:16:31 -0300",
      "bread": "2024-10-25 23:07:21 -0300",
      "golden_apple": "2024-10-25 23:08:20 -0300",
      "golden_carrot": "2024-10-26 15:39:44 -0300",
      "mushroom_stew": "2024-10-26 15:13:05 -0300",
      "carrot": "2024-10-26 15:09:07 -0300"
    },
    "done": false
  },
  "minecraft:husbandry/root": {
    "criteria": {
      "consumed_item": "2024-10-25 22:42:35 -0300"
    },
    "done": true
  },
  "minecraft:story/iron_tools": {
    "criteria": {
      "iron_pickaxe": "2024-10-25 22:44:19 -0300"
    },
    "done": true
  },
  "champions:kill_a_champion": {
    "criteria": {
      "kill_a_champion": "2024-10-25 22:48:45 -0300"
    },
    "done": true
  },
  "minecraft:story/mine_diamond": {
    "criteria": {
      "diamond": "2024-10-25 23:05:53 -0300"
    },
    "done": true
  },
  "lootr:1chest": {
    "criteria": {
      "opened_chest": "2024-10-25 23:07:00 -0300"
    },
    "done": true
  },
  "lootr:social": {
    "criteria": {
      "opened_barrel": "2024-10-25 23:07:07 -0300",
      "opened_chest": "2024-10-25 23:07:00 -0300"
    },
    "done": false
  },
  "lootr:1barrel": {
    "criteria": {
      "opened_barrel": "2024-10-25 23:07:07 -0300"
    },
    "done": true
  },
  "minecraft:story/obtain_armor": {
    "criteria": {
      "iron_leggings": "2024-10-25 23:11:48 -0300"
    },
    "done": true
  },
  "lootr:10loot": {
    "criteria": {
      "loot_stat": "2024-10-25 23:13:25 -0300"
    },
    "done": true
  },
  "enigmaticlegacy:main/all_spellstones": {
    "criteria": {
      "spellstone1": "2024-10-25 23:14:19 -0300"
    },
    "done": false
  },
  "enigmaticlegacy:main/discover_spellstone": {
    "criteria": {
      "spellstone": "2024-10-25 23:14:19 -0300"
    },
    "done": true
  },
  "enigmaticlegacy:book/relics/the_cube": {
    "criteria": {
      "has_item_1": "2024-10-25 23:14:19 -0300"
    },
    "done": false
  },
  "enigmaticlegacy:book/relics/golem_heart": {
    "criteria": {
      "has_items": "2024-10-25 23:14:19 -0300"
    },
    "done": true
  },
  "born_in_chaos_v1:junior_summoner": {
    "criteria": {
      "junior_summoner_0": "2024-10-25 23:24:10 -0300"
    },
    "done": true
  },
  "miningmaster:miningmaster/hidden_power": {
    "criteria": {
      "has_gem": "2024-10-25 23:25:03 -0300"
    },
    "done": true
  },
  "miningmaster:miningmaster/infernal_archaeologist": {
    "criteria": {
      "miningmaster:power_pyrite": "2024-10-25 23:25:03 -0300"
    },
    "done": false
  },
  "miningmaster:miningmaster/the_collector": {
    "criteria": {
      "miningmaster:spirit_garnet": "2024-10-26 18:14:11 -0300",
      "miningmaster:power_pyrite": "2024-10-25 23:25:03 -0300",
      "miningmaster:fire_ruby": "2024-10-27 00:32:19 -0300",
      "miningmaster:lucky_citrine": "2024-10-26 18:14:46 -0300",
      "miningmaster:air_malachite": "2024-10-27 18:42:32 -0300",
      "miningmaster:haste_peridot": "2024-10-26 15:13:06 -0300"
    },
    "done": false
  },
  "enigmaticlegacy:book/relics/enigmatic_eye": {
    "criteria": {
      "impossible": "2024-10-25 23:31:54 -0300"
    },
    "done": true
  },
  "minecraft:story/deflect_arrow": {
    "criteria": {
      "deflected_projectile": "2024-10-26 00:13:34 -0300"
    },
    "done": true
  },
  "regions_unexplored:pioneer": {
    "criteria": {
      "shrubland": "2024-10-26 00:21:05 -0300",
      "pine_taiga": "2024-10-26 17:13:18 -0300",
      "grassy_beach": "2024-10-26 17:15:53 -0300",
      "blackwood_taiga": "2024-10-26 17:14:31 -0300",
      "ochard": "2024-10-26 00:17:39 -0300",
      "highland_fields": "2024-10-26 00:21:17 -0300",
      "sparse_redwoods": "2024-10-26 17:15:47 -0300",
      "deciduous_forest": "2024-10-27 16:29:03 -0300",
      "redwoods": "2024-10-26 17:13:54 -0300"
    },
    "done": false
  },
  "dungeons_enhanced:ambitious_explorer": {
    "criteria": {
      "entered_pillager_camp": "2024-10-26 15:36:58 -0300",
      "entered_mushroom_house": "2024-10-26 00:21:33 -0300",
      "entered_fishing_ship": "2024-10-27 18:46:09 -0300",
      "entered_desert_temple": "2024-10-26 00:47:41 -0300",
      "entered_watch_tower": "2024-10-26 00:25:46 -0300"
    },
    "done": false
  },
  "dungeons_enhanced:root": {
    "criteria": {
      "entered_mushroom_house": "2024-10-26 00:21:33 -0300"
    },
    "done": true
  },
  "dungeons_enhanced:rarest_structure": {
    "criteria": {
      "entered_mushroom_house": "2024-10-26 00:21:33 -0300"
    },
    "done": true
  },
  "lootr:25loot": {
    "criteria": {
      "loot_stat": "2024-10-26 00:22:07 -0300"
    },
    "done": true
  },
  "biomeswevegone:biomeswevegone/adventure/oh_the_biomes_weve_gone": {
    "criteria": {
      "biomeswevegone:sakura_grove": "2024-10-26 14:59:27 -0300",
      "biomeswevegone:zelkova_forest": "2024-10-26 23:53:03 -0300",
      "biomeswevegone:forgotten_forest": "2024-10-26 23:47:36 -0300",
      "biomeswevegone:coconino_meadow": "2024-10-26 23:52:02 -0300",
      "biomeswevegone:maple_taiga": "2024-10-26 23:52:34 -0300",
      "biomeswevegone:orchard": "2024-10-26 00:23:41 -0300",
      "biomeswevegone:weeping_witch_forest": "2024-10-26 17:33:45 -0300",
      "biomeswevegone:aspen_boreal": "2024-10-26 17:33:41 -0300",
      "biomeswevegone:dacite_ridges": "2024-10-26 23:52:36 -0300",
      "biomeswevegone:frosted_coniferous_forest": "2024-10-26 23:52:42 -0300",
      "biomeswevegone:allium_shrubland": "2024-10-26 16:49:01 -0300",
      "biomeswevegone:coniferous_forest": "2024-10-26 23:52:56 -0300"
    },
    "done": false
  },
  "biomeswevegone:biomeswevegone/adventure/root": {
    "criteria": {
      "biomeswevegone:orchard": "2024-10-26 00:23:41 -0300"
    },
    "done": true
  },
  "enigmaticlegacy:book/enchantments/generic": {
    "criteria": {
      "has_items": "2024-10-26 00:31:04 -0300"
    },
    "done": true
  },
  "morevillagers:all_workstations_get": {
    "criteria": {
      "brewingstand": "2024-10-26 00:31:41 -0300"
    },
    "done": false
  },
  "morevillagers:first_workstation_get": {
    "criteria": {
      "brewingstand": "2024-10-26 00:31:41 -0300"
    },
    "done": true
  },
  "minecraft:husbandry/tame_an_animal": {
    "criteria": {
      "tamed_animal": "2024-10-26 00:37:01 -0300"
    },
    "done": true
  },
  "minecraft:story/shiny_gear": {
    "criteria": {
      "diamond_leggings": "2024-10-26 00:42:15 -0300"
    },
    "done": true
  },
  "dungeons_enhanced:traps_and_curses": {
    "criteria": {
      "entered_desert_temple": "2024-10-26 00:47:41 -0300"
    },
    "done": true
  },
  "dungeons_enhanced:seven_world_wonders": {
    "criteria": {
      "entered_desert_temple": "2024-10-26 00:47:41 -0300"
    },
    "done": false
  },
  "artifacts:amateur_archaeologist": {
    "criteria": {
      "find_artifact": "2024-10-26 00:54:41 -0300"
    },
    "done": true
  },
  "nova_structures:root": {
    "criteria": {
      "nova_structures:adventure/find_tavern": "2024-10-26 10:18:53 -0300"
    },
    "done": true
  },
  "nova_structures:adventure/find_tavern": {
    "criteria": {
      "nova_structures:tavern_spruce": "2024-10-26 10:18:53 -0300"
    },
    "done": true
  },
  "minecraft:main/smilodon": {
    "criteria": {
      "killed_smilodon": "2024-10-26 10:22:39 -0300"
    },
    "done": true
  },
  "morevillagers:first_village": {
    "criteria": {
      "plains": "2024-10-26 11:09:58 -0300"
    },
    "done": true
  },
  "morevillagers:all_villages": {
    "criteria": {
      "plains": "2024-10-26 11:09:58 -0300"
    },
    "done": false
  },
  "iceandfire:iceandfire/bestiary": {
    "criteria": {
      "bestiary": "2024-10-26 11:11:26 -0300"
    },
    "done": true
  },
  "mostructures:tavern": {
    "criteria": {
      "tavern": "2024-10-26 11:11:40 -0300"
    },
    "done": true
  },
  "minecraft:husbandry/bred_all_animals": {
    "criteria": {
      "minecraft:cow": "2024-10-26 11:21:04 -0300"
    },
    "done": false
  },
  "minecraft:husbandry/breed_an_animal": {
    "criteria": {
      "bred": "2024-10-26 11:21:04 -0300"
    },
    "done": true
  },
  "lootr:50loot": {
    "criteria": {
      "loot_stat": "2024-10-26 14:59:05 -0300"
    },
    "done": true
  },
  "miningmaster:miningmaster/top_to_bottom": {
    "criteria": {
      "miningmaster:fire_ruby": "2024-10-27 00:32:19 -0300",
      "miningmaster:lucky_citrine": "2024-10-26 18:14:46 -0300",
      "miningmaster:spirit_garnet": "2024-10-26 18:14:11 -0300",
      "miningmaster:haste_peridot": "2024-10-26 15:13:06 -0300"
    },
    "done": false
  },
  "iceandfire:iceandfire/dragon_meal": {
    "criteria": {
      "bestiary": "2024-10-26 17:03:26 -0300"
    },
    "done": true
  },
  "mostructures:the_castle_in_the_sky": {
    "criteria": {
      "the_castle_in_the_sky": "2024-10-26 17:16:10 -0300"
    },
    "done": true
  },
  "minecraft:husbandry/plant_seed": {
    "criteria": {
      "wheat": "2024-10-26 21:04:26 -0300"
    },
    "done": true
  },
  "nameless_trinkets:obtain/dark_nelumbo": {
    "criteria": {
      "dark_nelumbo": "2024-10-26 21:05:54 -0300"
    },
    "done": true
  },
  "nameless_trinkets:obtain/root": {
    "criteria": {
      "obtain": "2024-10-26 21:05:54 -0300"
    },
    "done": true
  },
  "minecraft:main/fossil": {
    "criteria": {
      "plant_fossil": "2024-10-26 21:25:21 -0300"
    },
    "done": true
  },
  "deeperdarker:main/root": {
    "criteria": {
      "deep_dark": "2024-10-26 21:25:33 -0300"
    },
    "done": true
  },
  "minecraft:adventure/avoid_vibration": {
    "criteria": {
      "avoid_vibration": "2024-10-27 00:05:04 -0300"
    },
    "done": true
  },
  "minecraft:story/form_obsidian": {
    "criteria": {
      "obsidian": "2024-10-27 00:05:14 -0300"
    },
    "done": true
  },
  "nameless_trinkets:obtain/ice_cube": {
    "criteria": {
      "ice_cube": "2024-10-27 00:14:20 -0300"
    },
    "done": true
  },
  "nameless_trinkets:obtain/explosion_proof_jacket": {
    "criteria": {
      "explosion_proof_jacket": "2024-10-27 00:18:26 -0300"
    },
    "done": true
  },
  "terramity:warden_soul_advancement": {
    "criteria": {
      "warden_soul_advancement_0": "2024-10-27 15:59:28 -0300"
    },
    "done": true
  },
  "minecraft:story/enchant_item": {
    "criteria": {
      "enchanted_item": "2024-10-27 16:16:00 -0300"
    },
    "done": true
  },
  "minecraft:story/lava_bucket": {
    "criteria": {
      "lava_bucket": "2024-10-27 16:35:42 -0300"
    },
    "done": true
  },
  "simplyswords:simplyswords": {
    "criteria": {
      "requirement": "2024-10-27 16:52:15 -0300"
    },
    "done": true
  },
  "lootr:100loot": {
    "criteria": {
      "loot_stat": "2024-10-27 18:46:18 -0300"
    },
    "done": true
  },
  "deeperdarker:main/kill_warden": {
    "criteria": {
      "warden": "2024-10-27 19:50:31 -0300"
    },
    "done": true
  },
  "deeperdarker:main/kill_all_sculk_mobs": {
    "criteria": {
      "warden": "2024-10-27 19:50:31 -0300"
    },
    "done": false
  },
  "minecraft:nether/netherite_armor": {
    "criteria": {
      "netherite_armor": "2024-10-27 19:47:56 -0300"
    },
    "done": true
  },
  "DataVersion": 3465
}